execrequests/__init__.py
execrequests/config.py
execrequests/handler.py
exec_requests-0.0.7.dist-info/LICENSE
exec_requests-0.0.7.dist-info/METADATA
exec_requests-0.0.7.dist-info/WHEEL
exec_requests-0.0.7.dist-info/top_level.txt
exec_requests-0.0.7.dist-info/RECORD
